{"title":"categories","date":"2018-09-30T09:25:30.000Z","updated":"2020-01-31T12:42:33.598Z","comments":true,"path":"api/pages/categories.json","covers":null,"excerpt":null,"content":"<script>\n        document.querySelectorAll('.github-emoji')\n          .forEach(el => {\n            if (!el.dataset.src) { return; }\n            const img = document.createElement('img');\n            img.style = 'display:none !important;';\n            img.src = el.dataset.src;\n            img.addEventListener('error', () => {\n              img.remove();\n              el.style.color = 'inherit';\n              el.style.backgroundImage = 'none';\n              el.style.background = 'none';\n            });\n            img.addEventListener('load', () => {\n              img.remove();\n            });\n            document.body.appendChild(img);\n          });\n      </script>"}